sunstone/__init__.py
sunstone/_release.py
sunstone/dataframe.py
sunstone/datasets.py
sunstone/exceptions.py
sunstone/lineage.py
sunstone/pandas.py
sunstone/py.typed
sunstone/validation.py
sunstone_py-0.5.3.dist-info/licenses/LICENSE
sunstone_py-0.5.3.dist-info/METADATA
sunstone_py-0.5.3.dist-info/WHEEL
sunstone_py-0.5.3.dist-info/entry_points.txt
sunstone_py-0.5.3.dist-info/top_level.txt
sunstone_py-0.5.3.dist-info/RECORD
