Metadata-Version: 2.4
Name: sunstone-py
Version: 0.5.3
Summary: Python library for managing datasets with lineage tracking in Sunstone projects
Author-email: Sunstone Institute <stig@sunstone.institute>
License: MIT
Project-URL: Homepage, https://github.com/sunstoneinstitute/sunstone-py
Project-URL: Documentation, https://sunstoneinstitute.github.io/sunstone-py/
Project-URL: Repository, https://github.com/sunstoneinstitute/sunstone-py
Classifier: Development Status :: 4 - Beta
Classifier: Intended Audience :: Science/Research
Classifier: License :: OSI Approved :: MIT License
Classifier: Programming Language :: Python :: 3
Classifier: Programming Language :: Python :: 3.12
Classifier: Programming Language :: Python :: 3.13
Classifier: Programming Language :: Python :: 3.14
Requires-Python: >=3.12
License-File: LICENSE
Requires-Dist: frictionless>=5.18.1
Requires-Dist: google-auth>=2.43.0
Requires-Dist: pandas>=2.0.0
Requires-Dist: pyyaml>=6.0
Requires-Dist: requests>=2.31.0
Requires-Dist: ruamel-yaml>=0.18
Dynamic: license-file
